[
  {
    "id": 1,
    "company": "TechCorp",
    "date": "2020-10-12",
    "students": "alice@example.com"
  },
  {
    "id": 2,
    "company": "InnovateX",
    "date": "2020-10-15",
    "students": "bob@example.com"
  },
  {
    "id": 3,
    "company": "FutureTech",
    "date": "2020-10-18",
    "students": "carol@example.com"
  },
  {
    "id": 4,
    "company": "NexGen Solutions",
    "date": "2020-10-20",
    "students": "dave@example.com"
  },
  {
    "id": 5,
    "company": "QuantumSoft",
    "date": "2020-10-22",
    "students": "eve@example.com"
  },
  {
    "id": 6,
    "company": "BrightTech",
    "date": "2020-10-25",
    "students": "frank@example.com"
  },
  {
    "id": 7,
    "company": "GlobalNet",
    "date": "2020-10-27",
    "students": "grace@example.com"
  },
  {
    "id": 8,
    "company": "DataWorks",
    "date": "2020-10-30",
    "students": "hank@example.com"
  },
  {
    "id": 9,
    "company": "EvolveTech",
    "date": "2020-11-01",
    "students": "iris@example.com"
  },
  {
    "id": 10,
    "company": "PeakSystems",
    "date": "2020-11-03",
    "students": "jack@example.com"
  },
  {
    "id": 11,
    "company": "Synergy Solutions",
    "date": "2020-11-05",
    "students": "kelly@example.com"
  },
  {
    "id": 12,
    "company": "NextWave",
    "date": "2020-10-11",
    "students": "lisa@example.com"
  },
  {
    "id": 13,
    "company": "TechVision",
    "date": "2020-10-14",
    "students": "mike@example.com"
  },
  {
    "id": 14,
    "company": "CoreTech",
    "date": "2020-10-17",
    "students": "nina@example.com"
  },
  {
    "id": 15,
    "company": "Optima",
    "date": "2020-10-21",
    "students": "olivia@example.com"
  },
  {
    "id": 16,
    "company": "AccelTech",
    "date": "2020-10-24",
    "students": "paul@example.com"
  },
  {
    "id": 17,
    "company": "InfoWare",
    "date": "2020-10-28",
    "students": "quinn@example.com"
  },
  {
    "id": 18,
    "company": "Vertex Solutions",
    "date": "2020-10-31",
    "students": "rachel@example.com"
  },
  {
    "id": 19,
    "company": "Innovix",
    "date": "2020-11-02",
    "students": "steve@example.com"
  },
  {
    "id": 20,
    "company": "HorizonTech",
    "date": "2020-11-04",
    "students": "tina@example.com"
  }
]
